{
  "data_execucao": "2026-07-14",
  "janela_aplicada": {
    "inicio": "2026-07-13T00:00",
    "fim": "2026-07-14T19:05"
  },
  "itens": [
    {
      "fonte": "Planalto | Resenha Diaria",
      "categoria": "Legislacao Federal",
      "titulo": "Lei nº 15.468, de 13.7.2026",
      "data_publicacao": "2026-07-13",
      "resumo": "Altera a Lei de Diretrizes e Bases da Educação Nacional para incluir educação política e direitos da cidadania como componente curricular obrigatório da educação básica.",
      "boletins_confirmados": [],
      "motivo_filtragem": "Tema de educação básica, sem aderência direta às áreas de atuação do escritório.",
      "url": "http://www.planalto.gov.br/ccivil_03/_ato2023-2026/2026/lei/l15468.htm",
      "boletins": []
    },
    {
      "fonte": "Planalto | Resenha Diaria",
      "categoria": "Legislacao Federal",
      "titulo": "Lei nº 15.467, de 13.7.2026",
      "data_publicacao": "2026-07-13",
      "resumo": "Institui a Semana Nacional da Ética e da Cidadania, a ser comemorada anualmente na primeira semana de maio.",
      "boletins_confirmados": [],
      "motivo_filtragem": "Tema geral de ética e cidadania, sem aderência direta às áreas de atuação do escritório.",
      "url": "http://www.planalto.gov.br/ccivil_03/_ato2023-2026/2026/lei/l15467.htm",
      "boletins": []
    },
    {
      "fonte": "Banco Central | Normas",
      "categoria": "Financeiro e Mercado de Capitais",
      "titulo": "Comunicado n° 45.564, 14/7/2026",
      "data_publicacao": "2026-07-14T18:30",
      "resumo": "Divulga condições para a realização de operações compromissadas com instituições financeiras participantes do módulo Oferta Pública (Ofpub).",
      "boletins_confirmados": [
        "mercado-capitais-fundos"
      ],
      "motivo_filtragem": "Trata de condições para operações financeiras e instituições financeiras, aderente a mercado de capitais.",
      "url": "https://www.bcb.gov.br/estabilidadefinanceira/exibenormativo?tipo=Comunicado&numero=45564",
      "boletins": [
        "mercado-capitais-fundos"
      ]
    },
    {
      "fonte": "Banco Central | Normas",
      "categoria": "Financeiro e Mercado de Capitais",
      "titulo": "Comunicado n° 45.563, 14/7/2026",
      "data_publicacao": "2026-07-14T18:30",
      "resumo": "Divulga as condições de oferta pública para a realização de operações de swap para fins de rolagem do vencimento de 03/08/2026.",
      "boletins_confirmados": [
        "mercado-capitais-fundos"
      ],
      "motivo_filtragem": "Refere-se a condições de oferta pública e operações de swap, relevante para mercado de capitais.",
      "url": "https://www.bcb.gov.br/estabilidadefinanceira/exibenormativo?tipo=Comunicado&numero=45563",
      "boletins": [
        "mercado-capitais-fundos"
      ]
    },
    {
      "fonte": "Banco Central | Normas",
      "categoria": "Financeiro e Mercado de Capitais",
      "titulo": "Resolução CMN n° 5.329, 14/7/2026",
      "data_publicacao": "2026-07-14T18:05",
      "resumo": "Define encargos financeiros para financiamentos rurais com recursos de Fundos Constitucionais de Financiamento e ajusta normas do Manual de Crédito Rural.",
      "boletins_confirmados": [
        "mercado-capitais-fundos",
        "imobiliario-infraestrutura"
      ],
      "motivo_filtragem": "Define encargos financeiros e normas para financiamentos rurais com fundos, relevante para mercado de capitais e financiamento de projetos imobiliários/rurais.",
      "url": "https://www.bcb.gov.br/estabilidadefinanceira/exibenormativo?tipo=Resolu%C3%A7%C3%A3o%20CMN&numero=5329",
      "boletins": [
        "mercado-capitais-fundos"
      ]
    },
    {
      "fonte": "Banco Central | Normas",
      "categoria": "Financeiro e Mercado de Capitais",
      "titulo": "Comunicado n° 45.562, 14/7/2026",
      "data_publicacao": "2026-07-14T17:18",
      "resumo": "Divulga a data de início das operações dos sistemas de escrituração de duplicatas escriturais, conforme Resolução BCB nº 339/2023.",
      "boletins_confirmados": [
        "mercado-capitais-fundos"
      ],
      "motivo_filtragem": "Trata do início de operações de sistemas de escrituração de duplicatas, relevante para o mercado financeiro e meios de pagamento.",
      "url": "https://www.bcb.gov.br/estabilidadefinanceira/exibenormativo?tipo=Comunicado&numero=45562",
      "boletins": [
        "mercado-capitais-fundos"
      ]
    },
    {
      "fonte": "Banco Central | Normas",
      "categoria": "Financeiro e Mercado de Capitais",
      "titulo": "Comunicado n° 45.561, 14/7/2026",
      "data_publicacao": "2026-07-14T11:46",
      "resumo": "Divulga o resultado de leilões de swap.",
      "boletins_confirmados": [
        "mercado-capitais-fundos"
      ],
      "motivo_filtragem": "Divulga resultados de leilões de swap, relevante para o mercado de capitais.",
      "url": "https://www.bcb.gov.br/estabilidadefinanceira/exibenormativo?tipo=Comunicado&numero=45561",
      "boletins": [
        "mercado-capitais-fundos"
      ]
    },
    {
      "fonte": "Banco Central | Normas",
      "categoria": "Financeiro e Mercado de Capitais",
      "titulo": "Comunicado n° 45.560, 14/7/2026",
      "data_publicacao": "2026-07-14T11:30",
      "resumo": "Divulga a realização de leilão de Swap Cambial Tradicional para fins de rolagem.",
      "boletins_confirmados": [
        "mercado-capitais-fundos"
      ],
      "motivo_filtragem": "Divulga a realização de leilão de swap cambial, relevante para o mercado de capitais.",
      "url": "https://www.bcb.gov.br/estabilidadefinanceira/exibenormativo?tipo=Comunicado&numero=45560",
      "boletins": [
        "mercado-capitais-fundos"
      ]
    },
    {
      "fonte": "Banco Central | Normas",
      "categoria": "Financeiro e Mercado de Capitais",
      "titulo": "Comunicado n° 45.559, 14/7/2026",
      "data_publicacao": "2026-07-14T11:30",
      "resumo": "Divulga a realização de leilão de Swap Cambial Tradicional para fins de rolagem.",
      "boletins_confirmados": [
        "mercado-capitais-fundos"
      ],
      "motivo_filtragem": "Divulga a realização de leilão de swap cambial, relevante para o mercado de capitais.",
      "url": "https://www.bcb.gov.br/estabilidadefinanceira/exibenormativo?tipo=Comunicado&numero=45559",
      "boletins": [
        "mercado-capitais-fundos"
      ]
    },
    {
      "fonte": "Banco Central | Normas",
      "categoria": "Financeiro e Mercado de Capitais",
      "titulo": "Comunicado n° 45.558, 14/7/2026",
      "data_publicacao": "2026-07-14T09:47",
      "resumo": "Divulga nomes de pessoas eleitas ou nomeadas para cargos de administração em instituições autorizadas a funcionar, para recebimento de objeções.",
      "boletins_confirmados": [
        "mercado-capitais-fundos",
        "societario-ma"
      ],
      "motivo_filtragem": "Trata de nomeações para cargos de administração em instituições financeiras, relevante para governança e regulação bancária.",
      "url": "https://www.bcb.gov.br/estabilidadefinanceira/exibenormativo?tipo=Comunicado&numero=45558",
      "boletins": [
        "mercado-capitais-fundos",
        "societario-ma"
      ]
    },
    {
      "fonte": "Banco Central | Normas",
      "categoria": "Financeiro e Mercado de Capitais",
      "titulo": "Comunicado n° 45.557, 14/7/2026",
      "data_publicacao": "2026-07-14T09:46",
      "resumo": "Divulga nome aprovado de pessoas eleitas/nomeadas para cargos de órgãos estatutários ou contratuais de sociedades autorizadas a funcionar pelo Banco Central do Brasil.",
      "boletins_confirmados": [
        "mercado-capitais-fundos",
        "societario-ma"
      ],
      "motivo_filtragem": "Divulga aprovação de nomes para cargos em sociedades autorizadas pelo BCB, relevante para governança e regulação bancária.",
      "url": "https://www.bcb.gov.br/estabilidadefinanceira/exibenormativo?tipo=Comunicado&numero=45557",
      "boletins": [
        "mercado-capitais-fundos",
        "societario-ma"
      ]
    },
    {
      "fonte": "Banco Central | Normas",
      "categoria": "Financeiro e Mercado de Capitais",
      "titulo": "Comunicado n° 45.556, 14/7/2026",
      "data_publicacao": "2026-07-14T09:07",
      "resumo": "Divulga as Taxas Básicas Financeiras (TBF), os Redutores 'R' e as Taxas Referenciais (TR) relativos a 11, 12 e 13 de julho de 2026.",
      "boletins_confirmados": [
        "mercado-capitais-fundos"
      ],
      "motivo_filtragem": "Divulga taxas financeiras de referência, relevante para o mercado financeiro.",
      "url": "https://www.bcb.gov.br/estabilidadefinanceira/exibenormativo?tipo=Comunicado&numero=45556",
      "boletins": [
        "mercado-capitais-fundos"
      ]
    },
    {
      "fonte": "Banco Central | Normas",
      "categoria": "Financeiro e Mercado de Capitais",
      "titulo": "Comunicado n° 45.555, 13/7/2026",
      "data_publicacao": "2026-07-13T18:30",
      "resumo": "Divulga as condições de oferta pública para a realização de operações de swap para fins de rolagem do vencimento de 03/08/2026.",
      "boletins_confirmados": [
        "mercado-capitais-fundos"
      ],
      "motivo_filtragem": "Refere-se a condições de oferta pública e operações de swap, relevante para mercado de capitais.",
      "url": "https://www.bcb.gov.br/estabilidadefinanceira/exibenormativo?tipo=Comunicado&numero=45555",
      "boletins": [
        "mercado-capitais-fundos"
      ]
    },
    {
      "fonte": "Banco Central | Normas",
      "categoria": "Financeiro e Mercado de Capitais",
      "titulo": "Comunicado n° 45.554, 13/7/2026",
      "data_publicacao": "2026-07-13T18:30",
      "resumo": "Divulga condições para a realização de operações compromissadas com instituições financeiras participantes do módulo Oferta Pública (Ofpub).",
      "boletins_confirmados": [
        "mercado-capitais-fundos"
      ],
      "motivo_filtragem": "Trata de condições para operações financeiras e instituições financeiras, aderente a mercado de capitais.",
      "url": "https://www.bcb.gov.br/estabilidadefinanceira/exibenormativo?tipo=Comunicado&numero=45554",
      "boletins": [
        "mercado-capitais-fundos"
      ]
    },
    {
      "fonte": "Banco Central | Normas",
      "categoria": "Financeiro e Mercado de Capitais",
      "titulo": "Comunicado n° 45.553, 13/7/2026",
      "data_publicacao": "2026-07-13T15:04",
      "resumo": "Divulga nome de pessoa com interesse em assumir a condição de controlador de Sociedade de Crédito Direto, conforme pedido de autorização para funcionamento.",
      "boletins_confirmados": [
        "mercado-capitais-fundos",
        "societario-ma"
      ],
      "motivo_filtragem": "Divulga interesse em controle de SCD e pedido de autorização, relevante para regulação bancária e M&A.",
      "url": "https://www.bcb.gov.br/estabilidadefinanceira/exibenormativo?tipo=Comunicado&numero=45553",
      "boletins": [
        "mercado-capitais-fundos",
        "societario-ma"
      ]
    },
    {
      "fonte": "CCEE | Noticias",
      "categoria": "Energia e Recursos",
      "titulo": "Garanta sua vaga nos próximos cursos especializados da CCEE Academy",
      "data_publicacao": "2026-07-14",
      "resumo": "Capacitações presenciais em São Paulo abordam backoffice e geração própria no setor elétrico.",
      "boletins_confirmados": [],
      "motivo_filtragem": "Notícia sobre cursos internos da CCEE, sem relevância direta para as áreas de atuação do escritório.",
      "url": "https://www.ccee.org.br/-/garanta-sua-vaga-nos-proximos-cursos-especializados-da-ccee-academy",
      "boletins": []
    },
    {
      "fonte": "CCEE | Noticias",
      "categoria": "Energia e Recursos",
      "titulo": "Inscrições abertas: conquiste a Certificação de Operadores do Mercado 2026",
      "data_publicacao": "2026-07-13",
      "resumo": "Exame promovido pela CCEE Academy abre novas oportunidades para profissionais do setor elétrico e traz novidades no processo de recertificação.",
      "boletins_confirmados": [],
      "motivo_filtragem": "Notícia sobre certificação profissional, sem relevância direta para as áreas de atuação do escritório.",
      "url": "https://www.ccee.org.br/-/inscricoes-abertas-conquiste-a-certificacao-de-operadores-do-mercado-2026",
      "boletins": []
    },
    {
      "fonte": "Destaques do D.O.U.",
      "categoria": "Legislação Federal",
      "titulo": "LEI Nº 15.468, DE 13 DE JULHO DE 2026",
      "data_publicacao": "2026-07-14",
      "resumo": "Altera a Lei de Diretrizes e Bases da Educação Nacional para incluir educação política e direitos da cidadania como componente curricular obrigatório da educação básica.",
      "boletins_confirmados": [],
      "motivo_filtragem": "Lei sobre educação básica, sem aderência direta às áreas de atuação do escritório.",
      "url": "https://www.in.gov.br/web/dou/-/lei-n-15.468-de-13-de-julho-de-2026-718704159",
      "boletins": []
    },
    {
      "fonte": "Destaques do D.O.U.",
      "categoria": "Legislação Federal",
      "titulo": "LEI Nº 15.467, DE 13 DE JULHO DE 2026",
      "data_publicacao": "2026-07-14",
      "resumo": "Institui a Semana Nacional da Ética e da Cidadania, a ser comemorada anualmente na primeira semana de maio.",
      "boletins_confirmados": [],
      "motivo_filtragem": "Lei sobre tema geral de ética e cidadania, sem aderência direta às áreas de atuação do escritório.",
      "url": "https://www.in.gov.br/web/dou/-/lei-n-15.467-de-13-de-julho-de-2026-718710955",
      "boletins": []
    },
    {
      "fonte": "Destaques do D.O.U.",
      "categoria": "Legislação Federal",
      "titulo": "DESPACHOS DO PRESIDENTE DA REPÚBLICA",
      "data_publicacao": "2026-07-14",
      "resumo": "Mensagens de restituição ao Congresso Nacional de autógrafos de Projetos de Lei que se transformam nas Leis nº 15.467 e 15.468, de 13 de julho de 2026.",
      "boletins_confirmados": [],
      "motivo_filtragem": "Despachos presidenciais sobre sanção de leis já listadas, sem nova informação relevante para as áreas do escritório.",
      "url": "https://www.in.gov.br/web/dou/-/despachos-do-presidente-da-republica-718705395",
      "boletins": []
    },
    {
      "fonte": "Destaques do D.O.U.",
      "categoria": "Legislação Federal",
      "titulo": "PORTARIA IN/CC/PR Nº 40, DE 13 DE JULHO DE 2026",
      "data_publicacao": "2026-07-14",
      "resumo": "Realoca cargos e função comissionados executivos no âmbito da Imprensa Nacional da Casa Civil da Presidência da República.",
      "boletins_confirmados": [],
      "motivo_filtragem": "Portaria sobre realocação de cargos na Imprensa Nacional, sem aderência às áreas de atuação do escritório.",
      "url": "https://www.in.gov.br/web/dou/-/portaria-in/cc/pr-n-40-de-13-de-julho-de-2026-718705474",
      "boletins": []
    },
    {
      "fonte": "Destaques do D.O.U.",
      "categoria": "Legislação Federal",
      "titulo": "RETIFICAÇÃO",
      "data_publicacao": "2026-07-14",
      "resumo": "Retificação da Portaria IN/CC/PR nº 36, de 25 de junho de 2026, alterando o prazo de entrada em vigor para sete dias úteis.",
      "boletins_confirmados": [],
      "motivo_filtragem": "Retificação de portaria anterior, sem conteúdo temático relevante para as áreas do escritório.",
      "url": "https://www.in.gov.br/web/dou/-/retificacao-718710134",
      "boletins": []
    },
    {
      "fonte": "Destaques do D.O.U.",
      "categoria": "Legislação Federal",
      "titulo": "PORTARIA MAPA Nº 936, DE 13 DE JU",
      "data_publicacao": "2026-07-14",
      "resumo": "Título e resumo incompletos, impossível classificar com precisão.",
      "boletins_confirmados": [],
      "motivo_filtragem": "Título e resumo incompletos, impossível classificar com precisão.",
      "url": "https://www.in.gov.br/web/dou/-/portaria-mapa-n-936-de-13-de-julho-de-2026-718705474",
      "boletins": []
    },
    {
      "fonte": "Ministério da Fazenda | Notícias",
      "categoria": "Tributário",
      "titulo": "Receita Federal atualiza regras cadastrais do CNPJ",
      "data_publicacao": "2026-07-13",
      "resumo": "Nova instrução normativa da Receita Federal atualiza critérios para análise das informações registradas no CNPJ.",
      "boletins_confirmados": [
        "direito-tributario"
      ],
      "motivo_filtragem": "Notícia sobre atualização de regras cadastrais do CNPJ pela Receita Federal, relevante para direito tributário.",
      "url": "https://www.gov.br/fazenda/pt-br/assuntos/noticias/2026/julho/receita-federal-atualiza-regras-cadastrais-do-cnpj",
      "boletins": [
        "direito-tributario"
      ]
    },
    {
      "fonte": "Ministério da Fazenda | Notícias",
      "categoria": "Tributário",
      "titulo": "Receita Federal ajusta regras do contencioso administrativo para devedores contumazes",
      "data_publicacao": "2026-07-13",
      "resumo": "Portaria RFB 702/2026 amplia a competência das turmas recursais da DRJ-R para apreciação de casos de devedores contumazes.",
      "boletins_confirmados": [
        "direito-tributario",
        "contencioso-civel"
      ],
      "motivo_filtragem": "Ajuste de regras para contencioso administrativo tributário, relevante para direito tributário e contencioso cível.",
      "url": "https://www.gov.br/fazenda/pt-br/assuntos/noticias/2026/julho/receita-federal-ajusta-regras-do-contencioso-administrativo-para-devedores-contumazes",
      "boletins": [
        "contencioso-civel",
        "direito-tributario"
      ]
    },
    {
      "fonte": "Ministério da Fazenda | Notícias",
      "categoria": "Tributário",
      "titulo": "Receita Federal vai antecipar atividades para implantação do CNPJ Alfanumérico",
      "data_publicacao": "2026-07-13",
      "resumo": "Necessidade técnica altera o período de disponibilidade da base do CNPJ para a implementação do novo formato alfanumérico.",
      "boletins_confirmados": [
        "direito-tributario"
      ],
      "motivo_filtragem": "Notícia sobre implantação de novo formato de CNPJ pela Receita Federal, relevante para direito tributário.",
      "url": "https://www.gov.br/fazenda/pt-br/assuntos/noticias/2026/julho/receita-federal-vai-antecipar-atividades-para-implantacao-do-cnpj-alfanumerico",
      "boletins": [
        "direito-tributario"
      ]
    },
    {
      "fonte": "Ministério da Fazenda | Notícias",
      "categoria": "Tributário",
      "titulo": "Ministério da Fazenda amplia exigências de publicidade de apostas no país",
      "data_publicacao": "2026-07-13",
      "resumo": "Novas regras incluem a exibição obrigatória de frases advertências sobre a temática da publicidade de apostas.",
      "boletins_confirmados": [
        "regulatorio-oleo-gas",
        "propriedade-intelectual"
      ],
      "motivo_filtragem": "Ampliação de exigências regulatórias para publicidade de apostas, relevante para regulação setorial e, potencialmente, tecnologia/e-commerce.",
      "url": "https://www.gov.br/fazenda/pt-br/assuntos/noticias/2026/julho/ministerio-da-fazenda-amplia-exigencias-de-publicidade-de-apostas-no-pais",
      "boletins": [
        "regulatorio-oleo-gas",
        "propriedade-intelectual"
      ]
    },
    {
      "fonte": "CVM | Notícias",
      "categoria": "Financeiro e Mercado de Capitais",
      "titulo": "CVM recebe reforço de 30 novos servidores, e Medida Provisória cria mais 50 vagas de Inspetor Federal",
      "data_publicacao": "2026-07-14",
      "resumo": "Contratações integram Plano Emergencial de Reestruturação da Autarquia, com criação de novas vagas de Inspetor Federal.",
      "boletins_confirmados": [],
      "motivo_filtragem": "Notícia sobre contratação de servidores para a CVM, sem relevância direta para as áreas de atuação do escritório.",
      "url": "https://www.gov.br/cvm/pt-br/assuntos/noticias/2026/cvm-recebe-reforco-de-30-novos-servidores-e-medida-provisoria-cria-mais-50-vagas-de-inspetor-federal",
      "boletins": []
    },
    {
      "fonte": "CVM | Notícias",
      "categoria": "Financeiro e Mercado de Capitais",
      "titulo": "Sessão de Julgamento em 14/7",
      "data_publicacao": "2026-07-13",
      "resumo": "Processos serão julgados pela CVM a partir das 15h do dia 14 de julho.",
      "boletins_confirmados": [
        "mercado-capitais-fundos",
        "contencioso-civel"
      ],
      "motivo_filtragem": "Anúncio de sessão de julgamento da CVM, relevante para o mercado de capitais e contencioso.",
      "url": "https://www.gov.br/cvm/pt-br/assuntos/noticias/2026/sessao-de-julgamento-em-14-7",
      "boletins": [
        "mercado-capitais-fundos"
      ]
    },
    {
      "fonte": "CVM | Notícias",
      "categoria": "Financeiro e Mercado de Capitais",
      "titulo": "CVM e Anbima ampliam matriz objeto de acordo de cooperação sobre análise de ofertas públicas",
      "data_publicacao": "2026-07-13",
      "resumo": "Acordo de cooperação entre CVM e Anbima amplia o escopo de análise de ofertas públicas, em vigor desde 30/6/2026.",
      "boletins_confirmados": [
        "mercado-capitais-fundos"
      ],
      "motivo_filtragem": "Acordo entre CVM e Anbima sobre ofertas públicas, diretamente relevante para o mercado de capitais.",
      "url": "https://www.gov.br/cvm/pt-br/assuntos/noticias/2026/cvm-e-anbima-ampliam-matriz-objeto-de-acordo-de-cooperacao-sobre-analise-de-ofertas-publicas",
      "boletins": [
        "mercado-capitais-fundos"
      ]
    },
    {
      "fonte": "CVM | Notícias",
      "categoria": "Financeiro e Mercado de Capitais",
      "titulo": "Indisponibilidade temporária de acesso ao Sistema Empresas.NET",
      "data_publicacao": "2026-07-13",
      "resumo": "Sistema Empresas.NET estará fora do ar das 9h às 18h do dia 18/7 para manutenção.",
      "boletins_confirmados": [],
      "motivo_filtragem": "Aviso operacional sobre indisponibilidade de sistema da CVM, sem relevância temática para as áreas do escritório.",
      "url": "https://www.gov.br/cvm/pt-br/assuntos/noticias/2026/indisponibilidade-temporaria-de-acesso-ao-sistema-empresas.net",
      "boletins": []
    },
    {
      "fonte": "B3 | Ofícios e Comunicados",
      "categoria": "Financeiro e Mercado de Capitais",
      "titulo": "043-2026-VNC-Ofício Circular",
      "data_publicacao": "2026-07-14",
      "resumo": "Tratamento das carteiras de índices da B3 em virtude da Oferta Pública Unificada de Aquisição de Ações (OPA) da T4F ENTRETENIMENTO S.A.",
      "boletins_confirmados": [
        "mercado-capitais-fundos",
        "societario-ma"
      ],
      "motivo_filtragem": "Ofício circular da B3 sobre tratamento de carteiras de índices devido a uma OPA, relevante para mercado de capitais e societário/M&A.",
      "url": "https://www.b3.com.br/pt_br/regulacao/oficios-e-comunicados/#panel0a",
      "boletins": [
        "mercado-capitais-fundos"
      ]
    },
    {
      "fonte": "B3 | Ofícios e Comunicados",
      "categoria": "Financeiro e Mercado de Capitais",
      "titulo": "040-2026-VNC-Comunicado Externo",
      "data_publicacao": "2026-07-14",
      "resumo": "Novas versões das especificações técnicas do Market Data B3 (UMDF Binário, UMDF FIX/FAST e Conflated) estão disponíveis.",
      "boletins_confirmados": [
        "mercado-capitais-fundos",
        "propriedade-intelectual"
      ],
      "motivo_filtragem": "Atualização técnica de dados de mercado da B3, relevante para mercado de capitais e tecnologia.",
      "url": "https://www.b3.com.br/pt_br/regulacao/oficios-e-comunicados/#panel1a",
      "boletins": [
        "mercado-capitais-fundos"
      ]
    },
    {
      "fonte": "B3 | Ofícios e Comunicados",
      "categoria": "Financeiro e Mercado de Capitais",
      "titulo": "039-2026-VNC-Comunicado Externo",
      "data_publicacao": "2026-07-14",
      "resumo": "Alteração do tamanho mínimo para registro de ofertas diretas nos produtos ETF de Renda Variável, LAND3, MTSA3, BBDC3.",
      "boletins_confirmados": [
        "mercado-capitais-fundos"
      ],
      "motivo_filtragem": "Alteração de regras para registro de ofertas diretas, relevante para o mercado de capitais.",
      "url": "https://www.b3.com.br/pt_br/regulacao/oficios-e-comunicados/#panel2a",
      "boletins": [
        "mercado-capitais-fundos"
      ]
    },
    {
      "fonte": "B3 | Ofícios e Comunicados",
      "categoria": "Financeiro e Mercado de Capitais",
      "titulo": "038-2026-VPC-Ofício Circular",
      "data_publicacao": "2026-07-14",
      "resumo": "A fase de produção assistida do sistema de duplicatas escriturais terá início em 15/07/2026.",
      "boletins_confirmados": [
        "mercado-capitais-fundos"
      ],
      "motivo_filtragem": "Início de produção assistida de duplicatas escriturais, relevante para o mercado financeiro e crédito.",
      "url": "https://www.b3.com.br/pt_br/regulacao/oficios-e-comunicados/#panel3a",
      "boletins": [
        "mercado-capitais-fundos"
      ]
    },
    {
      "fonte": "B3 | Ofícios e Comunicados",
      "categoria": "Financeiro e Mercado de Capitais",
      "titulo": "037-2026-VPC-Ofício Circular",
      "data_publicacao": "2026-07-14",
      "resumo": "Mudanças na metodologia do Índice de Energia Elétrica, com alteração do método de ponderação para valor de mercado do free float.",
      "boletins_confirmados": [
        "mercado-capitais-fundos",
        "imobiliario-infraestrutura"
      ],
      "motivo_filtragem": "Mudança na metodologia de índice de energia elétrica, relevante para mercado de capitais e setor de energia.",
      "url": "https://www.b3.com.br/pt_br/regulacao/oficios-e-comunicados/#panel4a",
      "boletins": [
        "mercado-capitais-fundos"
      ]
    },
    {
      "fonte": "B3 | Ofícios e Comunicados",
      "categoria": "Financeiro e Mercado de Capitais",
      "titulo": "006-2026-VPE-Comunicado Externo",
      "data_publicacao": "2026-07-14",
      "resumo": "O Sistema do Balcão B3 entrará em regime de contingência total no ambiente de produção no dia 27/08/2026.",
      "boletins_confirmados": [],
      "motivo_filtragem": "Aviso operacional sobre regime de contingência da B3, sem relevância temática para as áreas do escritório.",
      "url": "https://www.b3.com.br/pt_br/regulacao/oficios-e-comunicados/#panel5a",
      "boletins": []
    },
    {
      "fonte": "ANP | Notícias",
      "categoria": "Energia e Recursos",
      "titulo": "ANP firma acordo com os Procons do Acre e do Amapá para fiscalização do abastecimento nos estados",
      "data_publicacao": "2026-07-14",
      "resumo": "A ANP estabelece parcerias com Procons para fiscalização do abastecimento de combustíveis, visando proteger o consumidor.",
      "boletins_confirmados": [
        "regulatorio-oleo-gas",
        "contencioso-civel"
      ],
      "motivo_filtragem": "Acordo da ANP para fiscalização de abastecimento, relevante para regulação de óleo e gás e direito do consumidor.",
      "url": "https://www.gov.br/anp/pt-br/canais_atendimento/imprensa/noticias-comunicados/anp-firma-acordo-com-os-procons-do-acre-e-do-amapa-para-fiscalizacao-do-abastecimento-nos-estados",
      "boletins": [
        "regulatorio-oleo-gas"
      ]
    },
    {
      "fonte": "ANP | Notícias",
      "categoria": "Energia e Recursos",
      "titulo": "\"ANP com VC - Postos\": aplicativo disponibiliza dados de postos e canal de denúncias ao consumidor",
      "data_publicacao": "2026-07-13",
      "resumo": "Aplicativo da ANP oferece dados de postos e canal de denúncias, promovendo transparência e proteção ao consumidor.",
      "boletins_confirmados": [
        "regulatorio-oleo-gas",
        "propriedade-intelectual",
        "contencioso-civel"
      ],
      "motivo_filtragem": "Lançamento de aplicativo da ANP para consumidores, relevante para regulação de óleo e gás, tecnologia e direito do consumidor.",
      "url": "https://www.gov.br/anp/pt-br/canais_atendimento/imprensa/noticias-comunicados/anp-com-vc-postos-aplicativo-disponibiliza-dados-de-postos-e-canal-de-denuncias-ao-consumidor",
      "boletins": [
        "regulatorio-oleo-gas"
      ]
    },
    {
      "fonte": "MME | Notícias",
      "categoria": "Energia e Recursos",
      "titulo": "Consulta pública do POTEE 2026 está aberta para contribuições da sociedade",
      "data_publicacao": "2026-07-14",
      "resumo": "Documento reúne recomendações técnicas para reforço e expansão das instalações de transmissão do Sistema Interligado Nacional.",
      "boletins_confirmados": [
        "imobiliario-infraestrutura",
        "regulatorio-oleo-gas"
      ],
      "motivo_filtragem": "Consulta pública sobre expansão de transmissão de energia, relevante para infraestrutura e regulação.",
      "url": "https://www.gov.br/mme/pt-br/assuntos/noticias/consulta-publica-do-potee-2026-esta-aberta-para-contribuicoes-da-sociedade",
      "boletins": [
        "imobiliario-infraestrutura"
      ]
    },
    {
      "fonte": "MME | Notícias",
      "categoria": "Energia e Recursos",
      "titulo": "Segurança alimentar: entenda o papel da mineração neste processo",
      "data_publicacao": "2026-07-13",
      "resumo": "A mineração fornece recursos fundamentais para o desenvolvimento da agricultura e segurança alimentar do país.",
      "boletins_confirmados": [
        "imobiliario-infraestrutura",
        "ambiental-esg"
      ],
      "motivo_filtragem": "Artigo sobre o papel da mineração na segurança alimentar, relevante para mineração e aspectos ESG.",
      "url": "https://www.gov.br/mme/pt-br/assuntos/noticias/seguranca-alimentar-entenda-o-papel-da-mineracao-neste-processo",
      "boletins": [
        "ambiental-esg",
        "imobiliario-infraestrutura"
      ]
    },
    {
      "fonte": "ANEEL | Últimas Notícias",
      "categoria": "Energia e Recursos",
      "titulo": "Aprovada Consulta Pública para estabelecer regras de participação no Prêmio ANEEL de Inovação 2026",
      "data_publicacao": "2026-07-14",
      "resumo": "A ANEEL aprovou consulta pública para definir regras de participação no Prêmio ANEEL de Inovação 2026.",
      "boletins_confirmados": [
        "regulatorio-oleo-gas"
      ],
      "motivo_filtragem": "Aprovação de consulta pública pela ANEEL, relevante para regulação do setor de energia.",
      "url": "https://www.gov.br/aneel/pt-br/assuntos/noticias/2026-defeso-eleitoral/aprovada-consulta-publica-para-estabelecer-regras-de-participacao-no-premio-aneel-de-inovacao-2026",
      "boletins": [
        "regulatorio-oleo-gas"
      ]
    },
    {
      "fonte": "ANEEL | Últimas Notícias",
      "categoria": "Energia e Recursos",
      "titulo": "Revisão tarifária periódica da Energisa Sul-Sudeste é aprovada pela ANEEL",
      "data_publicacao": "2026-07-14",
      "resumo": "A ANEEL aprovou a revisão tarifária periódica da Energisa Sul-Sudeste, com novos índices em vigor a partir de 12 de julho.",
      "boletins_confirmados": [
        "regulatorio-oleo-gas",
        "imobiliario-infraestrutura"
      ],
      "motivo_filtragem": "Aprovação de revisão tarifária pela ANEEL, relevante para regulação e infraestrutura de energia.",
      "url": "https://www.gov.br/aneel/pt-br/assuntos/noticias/2026-defeso-eleitoral/revisao-tarifaria-periodica-da-energisa-sul-sudeste-e-aprovada-pela-aneel",
      "boletins": [
        "regulatorio-oleo-gas",
        "imobiliario-infraestrutura"
      ]
    },
    {
      "fonte": "ANEEL | Últimas Notícias",
      "categoria": "Energia e Recursos",
      "titulo": "Consulta Pública discutirá revisão da Metodologia do Fator X",
      "data_publicacao": "2026-07-14",
      "resumo": "Consulta Pública para discutir a revisão da Metodologia do Fator X, que incentiva empresas a reduzir custos e melhorar serviços.",
      "boletins_confirmados": [
        "regulatorio-oleo-gas",
        "contencioso-civel"
      ],
      "motivo_filtragem": "Consulta pública sobre metodologia de incentivo para empresas e consumidores, relevante para regulação e direito do consumidor.",
      "url": "https://www.gov.br/aneel/pt-br/assuntos/noticias/2026-defeso-eleitoral/consulta-publica-discutira-revisao-da-metodologia-do-fator-x",
      "boletins": [
        "regulatorio-oleo-gas"
      ]
    },
    {
      "fonte": "ANEEL | Últimas Notícias",
      "categoria": "Energia e Recursos",
      "titulo": "ANEEL estende o prazo de concessão da UHE Jirau (RO)",
      "data_publicacao": "2026-07-14",
      "resumo": "A ANEEL estendeu o prazo de concessão da Usina Hidrelétrica de Jirau, de dezembro de 2045 para agosto de 2047.",
      "boletins_confirmados": [
        "imobiliario-infraestrutura",
        "regulatorio-oleo-gas"
      ],
      "motivo_filtragem": "Extensão de prazo de concessão de usina hidrelétrica pela ANEEL, relevante para infraestrutura e regulação.",
      "url": "https://www.gov.br/aneel/pt-br/assuntos/noticias/2026-defeso-eleitoral/aneel-estende-o-prazo-de-concessao-da-uhe-jirau-ro",
      "boletins": [
        "regulatorio-oleo-gas",
        "imobiliario-infraestrutura"
      ]
    },
    {
      "fonte": "ANEEL | Últimas Notícias",
      "categoria": "Energia e Recursos",
      "titulo": "Agência aprova rescisão dos contratos entre comercializadora e agentes de distribuição",
      "data_publicacao": "2026-07-14",
      "resumo": "A ANEEL aprovou a rescisão de contratos entre comercializadora e agentes de distribuição devido a inadimplência contratual.",
      "boletins_confirmados": [
        "imobiliario-infraestrutura",
        "regulatorio-oleo-gas",
        "contencioso-civel"
      ],
      "motivo_filtragem": "Aprovação de rescisão contratual pela ANEEL devido a inadimplência, relevante para energia, regulação e contencioso.",
      "url": "https://www.gov.br/aneel/pt-br/assuntos/noticias/2026-defeso-eleitoral/agencia-aprova-rescisao-dos-contratos-entre-comercializadora-e-agentes-de-distribuicao",
      "boletins": [
        "regulatorio-oleo-gas",
        "imobiliario-infraestrutura"
      ]
    },
    {
      "fonte": "Ministério da Agricultura | Notícias",
      "categoria": "Regulatório e Setorial",
      "titulo": "Publicada portaria que define preços mínimos para os produtos de verão e regionais das safras 2026/27 e 2027",
      "data_publicacao": "2026-07-13",
      "resumo": "Portaria define preços mínimos para produtos agrícolas de verão e regionais para as safras 2026/27 e 2027.",
      "boletins_confirmados": [
        "ambiental-esg",
        "imobiliario-infraestrutura"
      ],
      "motivo_filtragem": "Portaria que define preços mínimos para produtos agrícolas, com impacto indireto em sustentabilidade e uso de terras rurais.",
      "url": "https://www.gov.br/agricultura/pt-br/assuntos/noticias/publicada-portaria-que-define-precos-minimos-para-os-produtos-de-verao-e-regionais-das-safras-2026-27-e-2027",
      "boletins": [
        "ambiental-esg"
      ]
    },
    {
      "fonte": "ANVISA | Notícias",
      "categoria": "Regulatório e Setorial",
      "titulo": "Soroterapia: promessas na internet NÃO substituem evidências científicas",
      "data_publicacao": "2026-07-14",
      "resumo": "Anvisa alerta sobre promessas de soroterapia na internet que não possuem evidências científicas.",
      "boletins_confirmados": [],
      "motivo_filtragem": "Notícia de alerta ao consumidor sobre saúde, sem aderência direta às áreas de atuação do escritório.",
      "url": "https://www.gov.br/anvisa/pt-br/assuntos/noticias-anvisa/2026/soroterapia-promessas-na-internet-nao-substituem-evidencias-cientificas",
      "boletins": []
    },
    {
      "fonte": "ANVISA | Notícias",
      "categoria": "Regulatório e Setorial",
      "titulo": "Autorizado, importado, experimental ou falsificado? Anvisa explica as diferenças entre os medicamentos",
      "data_publicacao": "2026-07-13",
      "resumo": "Anvisa esclarece as diferenças entre medicamentos autorizados, importados, experimentais e falsificados, e como identificá-los.",
      "boletins_confirmados": [
        "regulatorio-oleo-gas"
      ],
      "motivo_filtragem": "Esclarecimentos da Anvisa sobre medicamentos, relevante para regulação setorial e compliance.",
      "url": "https://www.gov.br/anvisa/pt-br/assuntos/noticias-anvisa/2026/autorizado-importado-experimental-ou-falsificado-anvisa-explica-as-diferencas-entre-os-medicamentos",
      "boletins": [
        "regulatorio-oleo-gas"
      ]
    },
    {
      "fonte": "ANVISA | Notícias",
      "categoria": "Regulatório e Setorial",
      "titulo": "Anvisa registra nova vacina contra a influenza",
      "data_publicacao": "2026-07-13",
      "resumo": "Anvisa registra nova vacina contra a influenza, indicada a partir dos 6 meses de idade.",
      "boletins_confirmados": [
        "regulatorio-oleo-gas"
      ],
      "motivo_filtragem": "Registro de nova vacina pela Anvisa, relevante para regulação setorial e autorizações.",
      "url": "https://www.gov.br/anvisa/pt-br/assuntos/noticias-anvisa/2026/anvisa-registra-nova-vacina-contra-a-influenza",
      "boletins": [
        "regulatorio-oleo-gas"
      ]
    },
    {
      "fonte": "ANVISA | Notícias",
      "categoria": "Regulatório e Setorial",
      "titulo": "Anvisa recebe delegação do Instituto de Salud Pública do Chile para intercâmbio técnico sobre dispositivos médicos",
      "data_publicacao": "2026-07-13",
      "resumo": "Anvisa recebeu delegação chilena para intercâmbio técnico sobre o ciclo regulatório de dispositivos médicos no Brasil.",
      "boletins_confirmados": [
        "regulatorio-oleo-gas"
      ],
      "motivo_filtragem": "Intercâmbio técnico da Anvisa sobre regulação de dispositivos médicos, relevante para regulação setorial.",
      "url": "https://www.gov.br/anvisa/pt-br/assuntos/noticias-anvisa/2026/anvisa-recebe-delegacao-do-instituto-de-salud-publica-do-chile-para-intercambio-tecnico-sobre-dispositivos-medicos",
      "boletins": [
        "regulatorio-oleo-gas"
      ]
    },
    {
      "fonte": "ANVISA | Notícias",
      "categoria": "Regulatório e Setorial",
      "titulo": "Anvisa assina novo Memorando de Entendimento com agência de Moçambique",
      "data_publicacao": "2026-07-13",
      "resumo": "Anvisa assina Memorando de Entendimento com agência de Moçambique para avaliação de produtos e intercâmbio de informações regulatórias.",
      "boletins_confirmados": [
        "regulatorio-oleo-gas"
      ],
      "motivo_filtragem": "Acordo de cooperação internacional da Anvisa sobre vigilância sanitária e informações regulatórias, relevante para regulação setorial.",
      "url": "https://www.gov.br/anvisa/pt-br/assuntos/noticias-anvisa/2026/anvisa-assina-novo-memorando-de-entendimento-com-agencia-de-mocambique",
      "boletins": [
        "regulatorio-oleo-gas"
      ]
    },
    {
      "fonte": "INPI | Notícias",
      "categoria": "Regulatório e Setorial",
      "titulo": "Retomado trâmite prioritário de patentes de Técnica de Comunicação Elétrica (H04 )",
      "data_publicacao": "2026-07-13T17:23",
      "resumo": "O INPI retomou o trâmite prioritário para patentes relacionadas à Técnica de Comunicação Elétrica (H04).",
      "boletins_confirmados": [
        "propriedade-intelectual"
      ],
      "motivo_filtragem": "Retomada de trâmite prioritário de patentes no INPI, diretamente relevante para propriedade intelectual.",
      "url": "https://www.gov.br/inpi/pt-br/central-de-conteudo/noticias/retoramado-tramite-prioritario-de-patentes-de-tecnica-de-comunicacao-eletrica-h04",
      "boletins": [
        "propriedade-intelectual"
      ]
    },
    {
      "fonte": "EPE | Notícias",
      "categoria": "Energia e Recursos",
      "titulo": "Mineralização de carbono é tema de nova publicação da EPE",
      "data_publicacao": "2026-07-14",
      "resumo": "Publicação da EPE aborda os fundamentos da mineralização de carbono como alternativa de armazenamento permanente de CO₂.",
      "boletins_confirmados": [
        "ambiental-esg"
      ],
      "motivo_filtragem": "Publicação sobre mineralização de carbono e armazenamento de CO2, diretamente relevante para temas ambientais e ESG.",
      "url": "https://www.epe.gov.br/pt/imprensa/noticias/mineralizacao-de-carbono-e-tema-de-nova-publicacao-da-epe",
      "boletins": [
        "ambiental-esg"
      ]
    },
    {
      "fonte": "EPE | Notícias",
      "categoria": "Energia e Recursos",
      "titulo": "EPE recebe representante de Moçambique para reunião sobre planejamento energético",
      "data_publicacao": "2026-07-14",
      "resumo": "A EPE recebeu representante de Moçambique para discutir planejamento energético e cooperação internacional.",
      "boletins_confirmados": [
        "imobiliario-infraestrutura",
        "regulatorio-oleo-gas"
      ],
      "motivo_filtragem": "Reunião sobre planejamento energético, relevante para infraestrutura e regulação do setor de energia.",
      "url": "https://www.epe.gov.br/pt/imprensa/noticias/epe-recebe-representante-de-mocambique-para-reuniao-sobre-planejamento-energetico",
      "boletins": [
        "imobiliario-infraestrutura"
      ]
    }
  ],
  "fontes_sem_publicacao_hoje": [
    {
      "fonte": "ANPD | Notícias",
      "motivo": "Nenhuma notícia publicada dentro da janela temporal."
    },
    {
      "fonte": "ONS | Notícias",
      "motivo": "Nenhuma notícia publicada dentro da janela temporal."
    },
    {
      "fonte": "COAF | Notícias",
      "motivo": "Nenhuma notícia publicada dentro da janela temporal."
    },
    {
      "fonte": "ANM | Notícias",
      "motivo": "Nenhuma notícia publicada dentro da janela temporal."
    }
  ],
  "fontes_sem_resultado": [
    {
      "fonte": "Receita Federal | Normas",
      "motivo": "A página é uma interface de busca e não apresenta normas publicadas dentro da janela temporal."
    },
    {
      "fonte": "CGU | Notícias",
      "motivo": "A página apresenta conteúdo restrito e não foi possível extrair notícias."
    },
    {
      "fonte": "Ministério do Meio Ambiente | Notícias",
      "motivo": "A página apresenta conteúdo restrito e não foi possível extrair notícias."
    },
    {
      "fonte": "SENACON | Notícias",
      "motivo": "A página apresenta conteúdo restrito e não foi possível extrair notícias."
    }
  ],
  "fontes_com_erro_tecnico": [],
  "boletins_config": {
    "boletins_disponiveis": [
      "trabalhista-empresarial",
      "direito-tributario",
      "societario-ma",
      "mercado-capitais-fundos",
      "regulatorio-oleo-gas",
      "imobiliario-infraestrutura",
      "ambiental-esg",
      "propriedade-intelectual",
      "contencioso-civel"
    ],
    "fontes_email_pendentes": {
      "trabalhista-empresarial": [],
      "direito-tributario": [
        "Tributário.com"
      ],
      "societario-ma": [
        "Latin Lawyer",
        "Agência iNFRA"
      ],
      "mercado-capitais-fundos": [
        "Latin Lawyer"
      ],
      "regulatorio-oleo-gas": [
        "iNFRA Energia"
      ],
      "imobiliario-infraestrutura": [
        "Agência iNFRA",
        "iNFRA Energia",
        "IRIB"
      ],
      "ambiental-esg": [
        "RC Ambiental"
      ],
      "propriedade-intelectual": [],
      "contencioso-civel": [
        "Tributário.com"
      ]
    },
    "mapeamento_fonte_boletim": {
      "Planalto | Resenha Diaria": [
        "trabalhista-empresarial",
        "direito-tributario",
        "societario-ma",
        "mercado-capitais-fundos",
        "regulatorio-oleo-gas",
        "imobiliario-infraestrutura",
        "ambiental-esg",
        "propriedade-intelectual",
        "contencioso-civel"
      ],
      "Destaques do D.O.U.": [
        "trabalhista-empresarial",
        "direito-tributario",
        "regulatorio-oleo-gas",
        "contencioso-civel"
      ],
      "Ministério da Fazenda | Notícias": [
        "trabalhista-empresarial",
        "direito-tributario",
        "societario-ma",
        "mercado-capitais-fundos",
        "regulatorio-oleo-gas",
        "imobiliario-infraestrutura",
        "ambiental-esg",
        "propriedade-intelectual",
        "contencioso-civel"
      ],
      "CGU | Notícias": [
        "trabalhista-empresarial",
        "regulatorio-oleo-gas"
      ],
      "Receita Federal | Normas": [
        "direito-tributario"
      ],
      "Banco Central | Normas": [
        "direito-tributario",
        "societario-ma",
        "mercado-capitais-fundos"
      ],
      "COAF | Notícias": [
        "direito-tributario",
        "mercado-capitais-fundos"
      ],
      "CVM | Notícias": [
        "mercado-capitais-fundos"
      ],
      "B3 | Ofícios e Comunicados": [
        "mercado-capitais-fundos"
      ],
      "ANP | Notícias": [
        "regulatorio-oleo-gas",
        "imobiliario-infraestrutura",
        "ambiental-esg"
      ],
      "ANEEL | Últimas Notícias": [
        "regulatorio-oleo-gas",
        "imobiliario-infraestrutura",
        "ambiental-esg"
      ],
      "ANM | Notícias": [
        "regulatorio-oleo-gas",
        "imobiliario-infraestrutura",
        "ambiental-esg"
      ],
      "ANVISA | Notícias": [
        "regulatorio-oleo-gas"
      ],
      "SENACON | Notícias": [
        "regulatorio-oleo-gas",
        "propriedade-intelectual",
        "contencioso-civel"
      ],
      "Secretaria de Prêmios e Apostas | Notícias": [
        "regulatorio-oleo-gas"
      ],
      "ONS | Notícias": [
        "imobiliario-infraestrutura",
        "ambiental-esg"
      ],
      "CCEE | Noticias": [
        "imobiliario-infraestrutura",
        "ambiental-esg"
      ],
      "EPE | Notícias": [
        "imobiliario-infraestrutura",
        "ambiental-esg"
      ],
      "MME | Notícias": [
        "imobiliario-infraestrutura",
        "ambiental-esg"
      ],
      "Ministério do Meio Ambiente | Notícias": [
        "ambiental-esg"
      ],
      "Ministério da Agricultura | Notícias": [
        "ambiental-esg"
      ],
      "INPI | Notícias": [
        "propriedade-intelectual"
      ],
      "ANPD | Notícias": [
        "propriedade-intelectual"
      ]
    }
  },
  "estatisticas_por_boletim": {
    "trabalhista-empresarial": {
      "total": 0
    },
    "direito-tributario": {
      "total": 3
    },
    "societario-ma": {
      "total": 3
    },
    "mercado-capitais-fundos": {
      "total": 20
    },
    "regulatorio-oleo-gas": {
      "total": 12
    },
    "imobiliario-infraestrutura": {
      "total": 6
    },
    "ambiental-esg": {
      "total": 3
    },
    "propriedade-intelectual": {
      "total": 2
    },
    "contencioso-civel": {
      "total": 1
    }
  }
}