{
  "data_execucao": "2026-06-27",
  "executado_em": "2026-06-27T18:57:14.906327-03:00",
  "janela": {
    "inicio": "2026-06-26T00:00",
    "fim": "2026-06-27T18:57"
  },
  "fontes_processadas": [
    {
      "fonte": "Planalto | Resenha Diária",
      "status": "ok",
      "tamanho_chars": 8536
    },
    {
      "fonte": "Destaques do D.O.U.",
      "status": "ok",
      "tamanho_chars": 247
    },
    {
      "fonte": "Receita Federal | Normas",
      "status": "ok",
      "tamanho_chars": 10000
    },
    {
      "fonte": "Ministério da Fazenda | Notícias",
      "status": "ok",
      "tamanho_chars": 10000
    },
    {
      "fonte": "ANPD | Notícias",
      "status": "ok",
      "tamanho_chars": 10000
    },
    {
      "fonte": "Banco Central | Normas",
      "status": "ok",
      "tamanho_chars": 7762
    },
    {
      "fonte": "CVM | Notícias",
      "status": "ok",
      "tamanho_chars": 10000
    },
    {
      "fonte": "B3 | Ofícios e Comunicados",
      "status": "ok",
      "tamanho_chars": 9862
    },
    {
      "fonte": "CGU | Notícias",
      "status": "ok",
      "tamanho_chars": 10000
    },
    {
      "fonte": "ANP | Notícias",
      "status": "ok",
      "tamanho_chars": 10000
    },
    {
      "fonte": "MME | Notícias",
      "status": "ok",
      "tamanho_chars": 10000
    },
    {
      "fonte": "ONS | Notícias",
      "status": "ok",
      "tamanho_chars": 5316
    },
    {
      "fonte": "ANEEL | Últimas Notícias",
      "status": "ok",
      "tamanho_chars": 10000
    },
    {
      "fonte": "CCEE | Notícias",
      "status": "ok",
      "tamanho_chars": 5009
    },
    {
      "fonte": "Secretaria de Prêmios e Apostas | Notícias",
      "status": "ok",
      "tamanho_chars": 10000
    },
    {
      "fonte": "Ministério do Meio Ambiente | Notícias",
      "status": "ok",
      "tamanho_chars": 10000
    },
    {
      "fonte": "Ministério da Agricultura | Notícias",
      "status": "ok",
      "tamanho_chars": 10000
    },
    {
      "fonte": "ANVISA | Notícias",
      "status": "ok",
      "tamanho_chars": 10000
    },
    {
      "fonte": "INPI | Notícias",
      "status": "ok",
      "tamanho_chars": 10000
    },
    {
      "fonte": "SENACON | Notícias",
      "status": "ok",
      "tamanho_chars": 10000
    },
    {
      "fonte": "COAF | Notícias",
      "status": "ok",
      "tamanho_chars": 10000
    },
    {
      "fonte": "ANM | Notícias",
      "status": "ok",
      "tamanho_chars": 10000
    },
    {
      "fonte": "EPE | Notícias",
      "status": "ok",
      "tamanho_chars": 9489
    }
  ],
  "resultado": {
    "itens_aceitos": 40,
    "itens_descartados_pos_validacao": 0,
    "fontes_sem_resultado": 7
  }
}